dirstuff/__init__.py
dirstuff/_cli/__init__.py
dirstuff/_cli/main.py
dirstuff/os/__init__.py
dirstuff/os/filesystem.py
dirstuff/summary/__init__.py
dirstuff/summary/filter_criteria.py
dirstuff/summary/memory_utilities.py
dirstuff/summary/parser.py
dirstuff/summary/tree.py
dirstuff-0.2.0.dist-info/WHEEL
dirstuff-0.2.0.dist-info/entry_points.txt
dirstuff-0.2.0.dist-info/LICENSE.txt
dirstuff-0.2.0.dist-info/METADATA
dirstuff-0.2.0.dist-info/RECORD
