Metadata-Version: 2.1
Name: dirstuff
Version: 0.2.0
Summary: Directory summary tool.
Home-page: https://github.com/gregorybchris/dirstuff
License: Apache Software License
Keywords: directory,file,summary
Author: Chris Gregory
Author-email: christopher.b.gregory@gmail.com
Requires-Python: >=3.11
Classifier: Intended Audience :: Developers
Classifier: License :: Other/Proprietary License
Classifier: Programming Language :: Python
Classifier: Programming Language :: Python :: 3
Classifier: Programming Language :: Python :: 3.11
Classifier: Programming Language :: Python :: 3.11
Classifier: Topic :: Software Development
Requires-Dist: click (>=8.1.0,<9.0.0)
Requires-Dist: colorama (>=0.4.0,<0.5.0)
Project-URL: Repository, https://github.com/gregorybchris/dirstuff
